<?xml version="1.0" encoding="UTF-8" standalone="no"?>
<pk><wd nm="terminal" rd="447,0:544"/><wd nm="terminate" rd="274,0:10454"/><wd nm="terminologie" rd="296,0:2499"/><wd nm="terminology" rd="15,0:7292|120,0:2534"/><wd nm="tes" rd="156,0:4372|374,0:260"/><wd nm="test" rd="22,193:3,46,61,83,239,377,502|30,0:2488|34,64:380,682,1119,1416,2510,2680,2822,3448,3488,4161,4235,4436,4726,4865,4972,5231,5359,5647,5783,5841,5899,6069,6128,6377,6602,6874,6970,6999,7131,7242,7401,7502,7588,7769,8130,8448,8539,8663,8744,8938,9139,9475,9697,10987|63,0:1886|64,0:1271|86,0:84|112,0:1642|119,0:1078,1120,1376|120,0:1158|128,64:322,353,750|141,0:1675|154,64:239,617|156,0:257,506,1706,3578,3662,4306,4526,4553|160,0:2667|161,0:846|175,0:193|192,128:3,61,120,138,171,193,237,298,489|208,0:82,431,556,609,826,890,909,959|210,0:466|232,0:2032|233,0:354,699,4562|234,0:5189|236,0:604,713,1021|238,193:36,95,180,594,822,1081,1202,1322,1360,1554,1661,1703,2679,2712,2731,2766,2908,3398,3935,4385,4634,5668,6257,7005,7804,8520|246,0:2434,2778,2827,2926|247,0:2437,2781,2830,2929|251,193:11,45,72,235,272,362,485,577,598,1259,1291,1436,2308,2763,3095|260,0:1116|262,0:1762|282,0:778|283,0:991|315,64:2652,4430|330,0:45,195,229,330,407,502,630|342,129:8,45,65,104,134,364|354,0:3372,3842,3876,4037,4114,4770|375,0:1760|376,0:376|382,0:766,833|390,0:7814,9496|400,0:490|420,193:17,45,84,169,205,342,465,532,569,605,646,837,946,1749,2227,2566,2695|423,0:428|426,64:3252|442,0:2656,2777"/><wd nm="test&apos;" rd="208,0:315"/><wd nm="tests:example" rd="128,64:858"/><wd nm="tests:graph" rd="154,64:725"/><wd nm="tests:order" rd="251,64:2416"/><wd nm="tests:remot" rd="315,64:4538|426,64:3360"/><wd nm="tests:result" rd="34,64:9805"/><wd nm="tests:view" rd="420,64:1857"/><wd nm="tex" rd="239,0:175"/><wd nm="text" rd="2,0:279|15,64:4023,5576,5705,5874,6030,10057|17,0:459|18,0:605|28,0:1044,1134,1153|34,0:3738,3904,6684|42,0:586,633,980,1042,1071,1170,1207,1240,1303,1336|53,0:1754,1825|63,0:1851|65,0:1934,2038,2050|68,0:180,200,484|70,193:15,34,45,67,340,377,421,432,1076,1312,1431|73,0:1055,3759,3798,3866|80,0:923|81,0:496,790|83,0:248,298,609|84,0:100,933,985,1370,2698,2974,3026,3342,3387,3494,5309,5648,5700,6009,6054,6155,7911,7963|85,0:295,1241,3481,4025,4099,4201,4856,6190,6749,6823,6925,7650|88,0:1534|89,0:2299,2646,5656,5809,5908|96,64:157,421,1181|101,0:123,1048,1122,1410,2208,2460,2596,2671,2812,2911,2998,4794|107,0:503,968|108,0:572,1033|115,0:2450,2505,4220,4439,4914|116,0:2694,2749,4425|123,0:1488|134,193:15,45,75,225,327,453,986,1103,1242,1363|135,0:203|136,0:520,792,812|140,0:721|141,0:2308|147,0:536|156,0:4006,4061,4087|164,0:172,884|169,0:321|177,0:619|184,0:491,818,1019|187,0:2091,2391|191,0:5321,6072,8665|211,0:516,1614,2099,2104,2194|212,0:873,2145,2487,2492,2582|213,0:341|216,0:498,1816,2336,2426|217,0:757,2117,2631,2636,2726|218,0:2559|221,0:138|229,0:115,169,205,239,294|230,0:261,290|232,0:2189|233,0:1552,2052,2271,2296,2487,4719|234,0:2116,5346|238,0:3457|240,0:534|246,0:1192,6471|247,0:1195|250,0:724,840,973,1033,1310,1470,1693|251,0:722|252,0:652|255,0:1023|257,0:279|258,0:1200|259,0:1504|262,0:1886|271,0:328|274,0:8375,8668,8682,8691|282,0:935|283,0:337,1148|284,0:3329,3799|285,0:2384,4124,5438,5500|294,0:152,178|295,0:187|296,0:833|301,0:1313,1552,2168,2218,2608,3007,3715|315,0:380,790,1433|316,0:108|327,193:15,72,272,550,587,627,678,832,1392,1519,1643,2004,2143|330,0:317|332,0:2322,2541,2566,4979,5014,7516|334,0:170,208,236|339,193:12,64,112,230,268,322,362,468,653,813,884,952,1081,1620,1875,2032,2162,2301|350,0:2176,2395,2420,4666,4701,7687|351,0:627|353,0:2636,2855,2880,5098,5133,7966|354,0:283,2092,2427,2493,2522,2978,3030,3074,3455,3485,3492,3539,3708,4927|358,0:765|361,0:297|366,0:578,851|374,0:77,108,1114|375,193:0,28,43,102,287,433,532,639,723,812,2224,2445|376,0:531,642|381,1:31|389,0:826|402,0:1038,1410,1499,1528,2041,2052,2181,2251,2438,2565|406,0:396|409,0:331,828|410,0:357,537,573,1045|411,0:736,813|412,0:814,891|413,0:1083,1160|414,0:897,974|417,0:243,568,698,1056|421,0:1104|423,0:916,2114,2194,2396,3567|424,0:597,821|425,64:50,366,578,1080,1212|426,0:453,489,1512,1554|434,0:778,956,1051,1362|435,0:382|440,0:197,376,1932|442,0:757,1153,1243,3258|444,0:889,977,1749,2985|448,0:1694,1798,1820|449,0:1486,1751,1778"/><wd nm="text:find" rd="425,64:1902"/><wd nm="text:order" rd="375,64:2334"/><wd nm="text:replac" rd="327,64:1747"/><wd nm="text_order" rd="232,0:2174|233,0:4704|234,0:5331|262,0:1871|282,0:920|283,0:1133|354,0:4912"/><wd nm="th" rd="34,0:3156|39,0:194|41,0:472|63,0:1129|73,0:4950|80,0:546,602|85,0:2844,6151|115,0:3491|119,0:1269|135,0:172|138,0:137|176,0:163|190,0:1575|197,0:125|211,0:318|212,0:675|216,0:300|217,0:559|221,0:873|222,0:734|269,0:813|285,0:3618,3674|296,0:1293|332,0:896|374,0:1320|385,0:158|422,0:2718|423,0:618"/><wd nm="tha" rd="30,0:333|422,0:3871"/><wd nm="than" rd="7,0:129,210|30,0:982|34,0:4881|67,0:422|68,0:336|73,0:2557|76,0:401,3682|82,0:895|101,0:4199|109,0:786|119,0:1089|124,0:462|132,0:714|139,0:1440,4529|156,0:1281,3209|196,0:385,5905|199,0:97|222,0:814|233,0:1982,3797|238,0:2391|274,0:3381|284,0:671,2737|294,0:290|300,0:847|302,0:456,571|312,0:1255|315,0:2108|326,0:101|332,0:2252,10430,10548,10852|342,0:127|343,0:2913,3559|346,0:841|347,0:682|350,0:2106|352,0:376|353,0:311,2566|354,0:3356,3397|385,0:486|390,0:1581,7581|410,0:2172|442,0:578|447,0:223" sp="1"/><wd nm="that" rd="0,0:348|3,0:75|4,0:278,557,829,949|5,0:299|7,0:784|8,0:196|9,0:141|11,1:97|14,0:308|15,0:371,505,642,1312,1420,1641,2004,2083,2346,2601,3157,3567,3686,3799,4205,5291,5891,6018,6220,6296,6619,6808,6915,7057,7091,7197,7685|16,0:389|17,0:526|20,0:73|22,0:202|23,0:55|25,0:260,381|26,0:145,208|28,0:784|30,0:150,172,252,706,953,1235|31,0:500|33,0:59|34,0:310,480,763,1512,2080,2166,2685,3123,3255,3993,5090,5461,5668,6321,6625,6767,6843,6892,7281,7298|35,0:250,298|36,0:201,432|37,0:99,162|39,0:304|40,0:302,474,680,950|42,0:954|43,0:177|44,0:235,298,416|46,0:391,454|48,0:834|51,0:127,629,837|52,0:148|53,0:757,901,1038,1507,1712,1735,1967|54,0:522|55,0:249,312|57,0:180,356|63,0:921,1093,1766,2228|64,0:350,471,583,1114|65,0:913|66,0:267,398,591,678,1223,1479,2070,2153,2185,2317,2602|67,0:827,1206|68,0:286|73,0:298,1300,1344,1372,2363,3190,3266,3901,3932,4052,4580,4925,5195|74,0:465,647,786|75,0:576,1023|76,0:314,1006,1018,1028,1090,1211,1570,1856,2063,2816,2904,3009,3200,3327,3485,3644|77,0:411|78,0:127,394,658,869,937,984|79,1:357,420,501,564,692,755,1435,1532,1991,2243,2962,3022,3322,3882,4866,5305,6197,6289,6513,6588,6748,6776,7449,7744,8475,8635,9185|80,0:524,867|82,0:170,702,806,1049,1205,1244,1542,1626|83,0:260|84,0:937,2598,2733,2978,3760,5652,6420,7595,7915,8102,8220,8259|85,0:341,2061,2285,2715,3381,3538,4501,7226,8756,9275|86,0:303|87,0:211|88,0:236,274,352|89,0:457,767,1263,3675,3711,4828,4848,4944,5217,5965|91,0:195,294|94,0:530,1603,2182,2768|96,0:410|97,0:488,698,730,1392|101,0:372,1548,1848,2592,2863,3272,3417,4454,4646|104,0:475|105,0:96|106,1:55|109,0:237,379,454,1586|110,0:189,309,361,553|112,0:574,2467|115,0:1055,1097,1284,1490,1756,2332,3035,4682,5014,5179,5362,6089|116,0:1305,1347,1519,1725,1991,2576,4429,4899,5387,5570|117,0:196,734|119,0:1044,1326,2807,4118,4334,4398,4425|120,0:1559,1650,1912,1967,1994,2360,2462|121,0:603|123,0:590|126,0:85,263,558,581|127,0:338|130,0:366|131,0:123,557,593|132,0:504,601,905|133,0:196,225,362|134,0:967|135,0:391,438|136,0:317,603|137,0:232,420|138,0:468,630,673|139,0:191,423,1993,2036,2196,2364,3190,3600,3740,3828,4994,5901,6443|141,0:511,863,1636,1825,2361|142,0:213|147,0:278,379,620|148,0:361,485,1318,2702,2848,3082|150,0:690,897|151,0:302,1133|152,0:215,249,419,1328|153,0:231|155,0:715,1445,1512,1598,1694,1876,2023,2231,2331|156,0:86,959,1504,1686,2061,2324,3583,3782,4178,4570|158,0:139|160,0:212,506,2356,2471,3407|161,0:336|164,0:199,531,874,922|166,0:100|169,0:84|173,0:148|174,0:115|175,0:298,342|176,0:81|177,0:119,222,310,412,851|178,0:748|179,0:88|180,0:88|181,1:59|183,0:229|184,0:165,1023|187,0:2140,2205,2598,3129,3807|189,0:248,290,527|190,0:215,282,754,1053,1362,1549,1672,1840,2057,2097,2182,2648|191,0:1246,1352,1644|195,0:271|196,0:515,709,1016,1061,1283,2565,2655,2709,3327,3653,3979,4069,4123,4740,5179,5712,5816,6059,6216,6255,6555,6640,7074|199,0:646|200,0:122|202,0:1307,1373|203,1:66|208,0:945|209,0:330,409|210,0:337,551|211,0:1177,1384,1936,2155|212,0:1577,1708,1915,2543|213,0:125|216,0:989,1586,2138,2387|217,0:1250,1680,1887,2439,2687|218,0:150,435,494,562,734,887,1309,1696,1803,2469,2769,2891|219,0:95,123|221,0:820|223,0:69,486,600,924,1160,2105|224,0:187,247|225,64:1890,2527,2543,2963,3780|226,0:181,244|228,0:76,255,322|229,0:161,298|231,0:269|232,0:81,857|233,0:85,1121,2350,2443,3487|234,0:269,473,545,1277,1369,1766,2709,3174,3271,4312,4535|235,0:236|236,0:68,877,1034,1161|238,0:193,1688,2433,2511,3033,5389,5430|241,0:823,937,1081,1168,1259,1413|243,0:764|244,0:1261,1839,1987|245,0:312|246,0:563,625,1886,2666,3277,3498,4488,5045,5706,6214,6973,7358,7639,7651|247,0:565,627,1889,2669,3280,3501,4720,5277,5759,6346,7742,8172,8555,8581,8629,8668,8738,8819,9013,9025|248,0:878,1378,2164|249,0:937|250,0:397,1043,1321,1486,2028|251,0:1162|252,0:719|256,0:886,1414|257,0:395,958,1774,2298,2850,3496|258,0:1159|259,0:109,213,897|261,0:676|263,0:378,615,891,1007|265,0:509,1186|268,0:221|269,0:588,690,889,1205,1625,1749|270,1:63|271,0:114|273,0:98,739|274,0:109,244,566,1148,2335,2435,2936,3023,3060,3391,3453,3493,3687,4060,4519,5081,5419,5911,6530,7276,7377,7400,8029,9166,9638,9927,10108,10713|277,1:70|280,1:102|281,0:116,187|283,0:350|284,0:176,870,2961,3833|285,0:416,1909,3596,3786,4068,5036,5472|289,0:524,658,915|290,0:140,533|292,0:3159|294,0:239|295,0:560,1646|296,0:1097,1375,1768|297,0:179,755,1125|299,0:655|300,0:166,331,428,559,593,703,1647,2220|301,0:1292,2200,2561,2854,2863,3011,3607|303,0:70,718,758,981,1113,1231,2479,2555|306,0:350|307,0:105,279,724,893|308,0:89,223|309,0:93|310,0:868|311,0:311|312,0:885,930,1165,1451,1672,1850|313,0:278|315,0:905,1016,1447,1493,1707,1797,2082,2217,3078|325,0:202,374,528|326,0:332|327,0:1373|328,0:1239|330,0:433|332,0:233,838,2763,3051,3349,4044,5109,5132,5173,5429,5474,5522,5572,5617,6329,6614,6740,7431,7461,8796,9513,9691|337,0:154|338,0:642|339,64:116,211,272,456,550,709,1051,1856|343,0:741,1007,1557,1688,1923,2700,3352,3476|346,0:175,286,442,766|347,0:642,926|349,0:351|350,0:2617,2905,4792,4815,4856,5112,5157,5205,5255,5300,6149,6783,6910,7602,7632|353,0:242,281,1141,3077,3365,5225,5248,5289,5549,5594,5642,5692,5737,6448,7055,7181,7881,7911|354,0:287,610,701,1470,1774,1915,1980,2096,2346,2670,2790,2847,2982,3154,3243|358,0:281,924,1859,2344|365,1:76|371,1:61|374,0:112,365,895,1118,1248|375,0:137|376,0:194,221,396,535,637|377,0:271,1107,1223,1291,1295|378,0:439,644,929|379,0:70|380,0:59|381,0:94,355,438|382,0:492|383,0:56|384,0:515,542,973,1010,1118,1139,1199,1342|390,0:493,807,987,1133,2051,2373,3389,3567,4127,4508,4916,6748,6811,7254,8804,9021,10273,10409,11101,11632,11775|391,0:263|392,0:719,2656,2969,3721|393,0:275|394,1:51|395,0:57,105|402,0:200,1414,2457,2528|403,0:61,221|404,0:193|405,0:66,402|409,0:369,558,1165|410,0:264,370,710,1077,1294,2152|412,0:272|414,0:216,247,263|417,0:162,406,440,632,884,918|421,0:276,567|422,0:121,433,838,950,1079,1141,2516,2566,3039,3622|423,0:116,570,739,794,951,1163,1260,1529,1596,2768,3167|424,0:578,802|426,0:624,2090|428,0:205|429,0:741|434,0:200,280,313,483,677,1015,1258|435,0:155,441,594|440,0:1584,1604|442,0:202,556,1093,1394,2257,2574,3410,3683,4158|444,0:438,1143,1287,1316,1753,2212|446,0:539|448,0:337,647,1036,1272,1355,1484,1517|449,0:123,517,641,1182,1362|450,0:880,1301,1537,1569|451,0:94" sp="1"/></pk>